ringgpt/__init__.py
ringgpt/dataloader.py
ringgpt/prompt.py
ringgpt/ring.py
ringgpt-0.1.25.dist-info/METADATA
ringgpt-0.1.25.dist-info/WHEEL
ringgpt-0.1.25.dist-info/RECORD
